{"Dictionary":[{"PutRequest": {
                "Item": {
                    "Word": {
                        "S": "Grove"
                    },
                    "Definition": {
                        "S": " The original sense seems to have been  t>a lane cut through trees"}}}},{"PutRequest": {
                "Item": {
                    "Word": {
                        "S": "Grovy"
                    },
                    "Definition": {
                        "S": " Pertaining to, or resembling, a grove; situated in, or frequenting, groves."}}}},{"PutRequest": {
                "Item": {
                    "Word": {
                        "S": "Grow"
                    },
                    "Definition": {
                        "S": " To increase in size by a natural and organic process; to increase in bulk by the gradual assimilation of new matter into the living organism; -- said of animals and vegetables and their organs."}}}},{"PutRequest": {
                "Item": {
                    "Word": {
                        "S": "Grow"
                    },
                    "Definition": {
                        "S": " To cause to grow; to cultivate; to produce;  s>as, to  x>grow"}}}},{"PutRequest": {
                "Item": {
                    "Word": {
                        "S": "Growl"
                    },
                    "Definition": {
                        "S": " To utter a deep guttural sound, sa an angry dog; to give forth an angry, grumbling sound."}}}},{"PutRequest": {
                "Item": {
                    "Word": {
                        "S": "Growl"
                    },
                    "Definition": {
                        "S": " To express by growling."}}}},{"PutRequest": {
                "Item": {
                    "Word": {
                        "S": "Growl"
                    },
                    "Definition": {
                        "S": " The deep, threatening sound made by a surly dog; a grumbling sound."}}}},{"PutRequest": {
                "Item": {
                    "Word": {
                        "S": "Grown"
                    },
                    "Definition": {
                        "S": "  t>p. p."}}}},{"PutRequest": {
                "Item": {
                    "Word": {
                        "S": "Grub"
                    },
                    "Definition": {
                        "S": " To dig in or under the ground, generally for an object that is difficult to reach or extricate; to be occupied in digging."}}}},{"PutRequest": {
                "Item": {
                    "Word": {
                        "S": "Grub"
                    },
                    "Definition": {
                        "S": " To dig; to dig up by the roots; to root out by digging; -- followed by up;  s>as, to  x>grub"}}}},{"PutRequest": {
                "Item": {
                    "Word": {
                        "S": "Grub"
                    },
                    "Definition": {
                        "S": " The larva of an insect, especially of a beetle; -- called also grubworm. See  t>Illust."}}}},{"PutRequest": {
                "Item": {
                    "Word": {
                        "S": "Gruel"
                    },
                    "Definition": {
                        "S": " A light, liquid food, made by boiling meal of maize, oatmeal, or fiour in water or milk; thin porridge."}}}},{"PutRequest": {
                "Item": {
                    "Word": {
                        "S": "Gruf"
                    },
                    "Definition": {
                        "S": " Forwards; with one's face to the ground."}}}},{"PutRequest": {
                "Item": {
                    "Word": {
                        "S": "Gruff"
                    },
                    "Definition": {
                        "S": " Of a rough or stern manner, voice, or countenance; sour; surly; severe; harsh."}}}},{"PutRequest": {
                "Item": {
                    "Word": {
                        "S": "Grum"
                    },
                    "Definition": {
                        "S": " Morose; severe of countenance; sour; surly; glum; grim."}}}},{"PutRequest": {
                "Item": {
                    "Word": {
                        "S": "Grume"
                    },
                    "Definition": {
                        "S": " A thick, viscid fluid; a clot, as of blood."}}}},{"PutRequest": {
                "Item": {
                    "Word": {
                        "S": "Grunt"
                    },
                    "Definition": {
                        "S": " A deep, guttural sound, as of a hog."}}}},{"PutRequest": {
                "Item": {
                    "Word": {
                        "S": "Gry"
                    },
                    "Definition": {
                        "S": " A measure equal to one tenth of a line."}}}},{"PutRequest": {
                "Item": {
                    "Word": {
                        "S": "Gryde"
                    },
                    "Definition": {
                        "S": " To gride. See  r>Gride"}}}},{"PutRequest": {
                "Item": {
                    "Word": {
                        "S": "Grype"
                    },
                    "Definition": {
                        "S": " To gripe.  ark>[Obs.]"}}}},{"PutRequest": {
                "Item": {
                    "Word": {
                        "S": "Grype"
                    },
                    "Definition": {
                        "S": " A vulture; the griffin."}}}},{"PutRequest": {
                "Item": {
                    "Word": {
                        "S": "Guaco"
                    },
                    "Definition": {
                        "S": " A plant ( pn>Aristolochia anguicida"}}}},{"PutRequest": {
                "Item": {
                    "Word": {
                        "S": "Guan"
                    },
                    "Definition": {
                        "S": " Any one of many species of large gallinaceous birds of Certal and South America, belonging to  pn>Penelope"}}}},{"PutRequest": {
                "Item": {
                    "Word": {
                        "S": "Guana"
                    },
                    "Definition": {
                        "S": " See  r>Iguana"}}}},{"PutRequest": {
                "Item": {
                    "Word": {
                        "S": "Guano"
                    },
                    "Definition": {
                        "S": " A substance found in great abundance on some coasts or islands frequented by sea fowls, and composed chiefly of their excrement. It is rich in phosphates and ammonia, and is used as a powerful fertilize"}}}}]}