{"Dictionary":[{"PutRequest": {
                "Item": {
                    "Word": {
                        "S": "Lawm"
                    },
                    "Definition": {
                        "S": " A very fine linen (or sometimes cotton) fabric with a rather open texture. Lawn is used for the sleeves of a bishop's official dress in the English Church, and, figuratively, stands for the office itsel"}}}},{"PutRequest": {
                "Item": {
                    "Word": {
                        "S": "Lawnd"
                    },
                    "Definition": {
                        "S": " See  r>Laund"}}}},{"PutRequest": {
                "Item": {
                    "Word": {
                        "S": "Lawny"
                    },
                    "Definition": {
                        "S": " Having a lawn; characterized by a lawn or by lawns; like a lawn."}}}},{"PutRequest": {
                "Item": {
                    "Word": {
                        "S": "Lawny"
                    },
                    "Definition": {
                        "S": " Made of lawn or fine linen."}}}},{"PutRequest": {
                "Item": {
                    "Word": {
                        "S": "Lax"
                    },
                    "Definition": {
                        "S": " Not tense, firm, or rigid; loose; slack;  s>as, a  x>lax"}}}},{"PutRequest": {
                "Item": {
                    "Word": {
                        "S": "Lax"
                    },
                    "Definition": {
                        "S": " A looseness; diarrhea."}}}},{"PutRequest": {
                "Item": {
                    "Word": {
                        "S": "Laxly"
                    },
                    "Definition": {
                        "S": " In a lax manner."}}}},{"PutRequest": {
                "Item": {
                    "Word": {
                        "S": "Lay"
                    },
                    "Definition": {
                        "S": " of  r>Lie"}}}},{"PutRequest": {
                "Item": {
                    "Word": {
                        "S": "Lay"
                    },
                    "Definition": {
                        "S": " Of or pertaining to the laity, as distinct from the clergy;  s>as, a  x>lay"}}}},{"PutRequest": {
                "Item": {
                    "Word": {
                        "S": "Lay"
                    },
                    "Definition": {
                        "S": " The laity; the common people."}}}},{"PutRequest": {
                "Item": {
                    "Word": {
                        "S": "Lay"
                    },
                    "Definition": {
                        "S": " A meadow. See  r>Lea"}}}},{"PutRequest": {
                "Item": {
                    "Word": {
                        "S": "Lay"
                    },
                    "Definition": {
                        "S": " Faith; creed; religious profession."}}}},{"PutRequest": {
                "Item": {
                    "Word": {
                        "S": "Lay"
                    },
                    "Definition": {
                        "S": " A song; a simple lyrical poem; a ballad."}}}},{"PutRequest": {
                "Item": {
                    "Word": {
                        "S": "Lay"
                    },
                    "Definition": {
                        "S": " To cause to lie down, to be prostrate, or to lie against something; to put or set down; to deposit;  s>as, to  x>lay"}}}},{"PutRequest": {
                "Item": {
                    "Word": {
                        "S": "Lay"
                    },
                    "Definition": {
                        "S": " To produce and deposit eggs."}}}},{"PutRequest": {
                "Item": {
                    "Word": {
                        "S": "Lay"
                    },
                    "Definition": {
                        "S": " That which lies or is laid or is conceived of as having been laid or placed in its position; a row; a stratum; a layer;  s>as, a  x>lay"}}}},{"PutRequest": {
                "Item": {
                    "Word": {
                        "S": "Layer"
                    },
                    "Definition": {
                        "S": " One who, or that which, lays."}}}},{"PutRequest": {
                "Item": {
                    "Word": {
                        "S": "Lazar"
                    },
                    "Definition": {
                        "S": " A person infected with a filthy or pestilential disease; a leper."}}}},{"PutRequest": {
                "Item": {
                    "Word": {
                        "S": "Laze"
                    },
                    "Definition": {
                        "S": " To be lazy or idle."}}}},{"PutRequest": {
                "Item": {
                    "Word": {
                        "S": "Laze"
                    },
                    "Definition": {
                        "S": " To waste in sloth; to spend, as time, in idleness;  s>as, to  x>laze"}}}},{"PutRequest": {
                "Item": {
                    "Word": {
                        "S": "Lazy"
                    },
                    "Definition": {
                        "S": " Disinclined to action or exertion; averse to labor; idle; shirking work."}}}},{"PutRequest": {
                "Item": {
                    "Word": {
                        "S": "Lea"
                    },
                    "Definition": {
                        "S": " A measure of yarn; for linen, 300 yards; for cotton, 120 yards; a lay."}}}},{"PutRequest": {
                "Item": {
                    "Word": {
                        "S": "Lea"
                    },
                    "Definition": {
                        "S": " A meadow or sward land; a grassy field."}}}},{"PutRequest": {
                "Item": {
                    "Word": {
                        "S": "Leach"
                    },
                    "Definition": {
                        "S": " See 3d  r>Leech"}}}},{"PutRequest": {
                "Item": {
                    "Word": {
                        "S": "Leach"
                    },
                    "Definition": {
                        "S": " A quantity of wood ashes, through which water passes, and thus imbibes the alkali."}}}}]}