{"Dictionary":[{"PutRequest": {
                "Item": {
                    "Word": {
                        "S": "Yet"
                    },
                    "Definition": {
                        "S": " Nevertheless; notwithstanding; however."}}}},{"PutRequest": {
                "Item": {
                    "Word": {
                        "S": "Yeve"
                    },
                    "Definition": {
                        "S": " To give."}}}},{"PutRequest": {
                "Item": {
                    "Word": {
                        "S": "Yeven"
                    },
                    "Definition": {
                        "S": " Given."}}}},{"PutRequest": {
                "Item": {
                    "Word": {
                        "S": "Yew"
                    },
                    "Definition": {
                        "S": " See  r>Yaw"}}}},{"PutRequest": {
                "Item": {
                    "Word": {
                        "S": "Yew"
                    },
                    "Definition": {
                        "S": " An evergreen tree ( pn>Taxus baccata"}}}},{"PutRequest": {
                "Item": {
                    "Word": {
                        "S": "Yew"
                    },
                    "Definition": {
                        "S": " Of or pertaining to yew trees; made of the wood of a yew tree;  s>as, a  x>yew"}}}},{"PutRequest": {
                "Item": {
                    "Word": {
                        "S": "Yewen"
                    },
                    "Definition": {
                        "S": " Made of yew;  s>as,  x>yewen"}}}},{"PutRequest": {
                "Item": {
                    "Word": {
                        "S": "Yex"
                    },
                    "Definition": {
                        "S": " To hiccough."}}}},{"PutRequest": {
                "Item": {
                    "Word": {
                        "S": "Yex"
                    },
                    "Definition": {
                        "S": " A hiccough."}}}},{"PutRequest": {
                "Item": {
                    "Word": {
                        "S": "Yezdi"
                    },
                    "Definition": {
                        "S": " Same as  c>Izedi. "}}}},{"PutRequest": {
                "Item": {
                    "Word": {
                        "S": "Yfere"
                    },
                    "Definition": {
                        "S": " Together.  See  r>Ifere"}}}},{"PutRequest": {
                "Item": {
                    "Word": {
                        "S": "Yghe"
                    },
                    "Definition": {
                        "S": " Eye."}}}},{"PutRequest": {
                "Item": {
                    "Word": {
                        "S": "Ygo"
                    },
                    "Definition": {
                        "S": " Gone."}}}},{"PutRequest": {
                "Item": {
                    "Word": {
                        "S": "Yield"
                    },
                    "Definition": {
                        "S": " To give in return for labor expended; to produce, as payment or interest on what is expended or invested; to pay;  s>as, money at interest  x>yields"}}}},{"PutRequest": {
                "Item": {
                    "Word": {
                        "S": "Yield"
                    },
                    "Definition": {
                        "S": " To give up the contest; to submit; to surrender; to succumb."}}}},{"PutRequest": {
                "Item": {
                    "Word": {
                        "S": "Yield"
                    },
                    "Definition": {
                        "S": " Amount yielded; product; -- applied especially to products resulting from growth or cultivation."}}}},{"PutRequest": {
                "Item": {
                    "Word": {
                        "S": "Yift"
                    },
                    "Definition": {
                        "S": " Gift."}}}},{"PutRequest": {
                "Item": {
                    "Word": {
                        "S": "Yin"
                    },
                    "Definition": {
                        "S": " A Chinese weight of 2 23/ pounds."}}}},{"PutRequest": {
                "Item": {
                    "Word": {
                        "S": "Yis"
                    },
                    "Definition": {
                        "S": " Yes."}}}},{"PutRequest": {
                "Item": {
                    "Word": {
                        "S": "Yit"
                    },
                    "Definition": {
                        "S": " Yet."}}}},{"PutRequest": {
                "Item": {
                    "Word": {
                        "S": "Yite"
                    },
                    "Definition": {
                        "S": " The European yellow-hammer."}}}},{"PutRequest": {
                "Item": {
                    "Word": {
                        "S": "Yive"
                    },
                    "Definition": {
                        "S": " To give."}}}},{"PutRequest": {
                "Item": {
                    "Word": {
                        "S": "-yl"
                    },
                    "Definition": {
                        "S": " A suffix used as a characteristic termination of chemical radicals; as in eth >yl"}}}},{"PutRequest": {
                "Item": {
                    "Word": {
                        "S": "Yie"
                    },
                    "Definition": {
                        "S": " Isle."}}}},{"PutRequest": {
                "Item": {
                    "Word": {
                        "S": "Ymel"
                    },
                    "Definition": {
                        "S": " Among."}}}}]}