{"Dictionary":[{"PutRequest": {
                "Item": {
                    "Word": {
                        "S": "Kyd"
                    },
                    "Definition": {
                        "S": "  t>p. p."}}}},{"PutRequest": {
                "Item": {
                    "Word": {
                        "S": "Kydde"
                    },
                    "Definition": {
                        "S": "  t>imp."}}}},{"PutRequest": {
                "Item": {
                    "Word": {
                        "S": "Kyke"
                    },
                    "Definition": {
                        "S": " To look steadfastly; to gaze."}}}},{"PutRequest": {
                "Item": {
                    "Word": {
                        "S": "Kyley"
                    },
                    "Definition": {
                        "S": " A variety of the boomerang."}}}},{"PutRequest": {
                "Item": {
                    "Word": {
                        "S": "Kymry"
                    },
                    "Definition": {
                        "S": " See  r>Cymry"}}}},{"PutRequest": {
                "Item": {
                    "Word": {
                        "S": "Kyrie"
                    },
                    "Definition": {
                        "S": " See  r>Kyrie eleison"}}}},{"PutRequest": {
                "Item": {
                    "Word": {
                        "S": "Kythe"
                    },
                    "Definition": {
                        "S": " To come into view; to appear."}}}},{"PutRequest": {
                "Item": {
                    "Word": {
                        "S": "L"
                    },
                    "Definition": {
                        "S": " L is the twelfth letter of the English alphabet, and a vocal consonant. It is usually called a  >semivowel"}}}},{"PutRequest": {
                "Item": {
                    "Word": {
                        "S": "L"
                    },
                    "Definition": {
                        "S": " A short right-angled pipe fitting, used in connecting two pipes at right angles"}}}},{"PutRequest": {
                "Item": {
                    "Word": {
                        "S": "La"
                    },
                    "Definition": {
                        "S": " A syllable applied to the sixth tone of the scale in music in solmization."}}}},{"PutRequest": {
                "Item": {
                    "Word": {
                        "S": "La"
                    },
                    "Definition": {
                        "S": " An exclamation of surprise; -- commonly followed by  >me"}}}},{"PutRequest": {
                "Item": {
                    "Word": {
                        "S": "Laas"
                    },
                    "Definition": {
                        "S": " A lace. See  r>Lace"}}}},{"PutRequest": {
                "Item": {
                    "Word": {
                        "S": "Lab"
                    },
                    "Definition": {
                        "S": " To prate; to gossip; to babble; to blab."}}}},{"PutRequest": {
                "Item": {
                    "Word": {
                        "S": "Lab"
                    },
                    "Definition": {
                        "S": " A telltale; a prater; a blabber."}}}},{"PutRequest": {
                "Item": {
                    "Word": {
                        "S": "Label"
                    },
                    "Definition": {
                        "S": " A tassel."}}}},{"PutRequest": {
                "Item": {
                    "Word": {
                        "S": "Label"
                    },
                    "Definition": {
                        "S": " To affix a label to; to mark with a name, etc.;  s>as, to  x>label"}}}},{"PutRequest": {
                "Item": {
                    "Word": {
                        "S": "Labia"
                    },
                    "Definition": {
                        "S": " See  r>Labium"}}}},{"PutRequest": {
                "Item": {
                    "Word": {
                        "S": "Labor"
                    },
                    "Definition": {
                        "S": " Physical toil or bodily exertion, especially when fatiguing, irksome, or unavoidable, in distinction from sportive exercise; hard, muscular effort directed to some useful end, as agriculture, manufactur"}}}},{"PutRequest": {
                "Item": {
                    "Word": {
                        "S": "Labor"
                    },
                    "Definition": {
                        "S": " To exert muscular strength; to exert one's strength with painful effort, particularly in servile occupations; to work; to toil."}}}},{"PutRequest": {
                "Item": {
                    "Word": {
                        "S": "Labor"
                    },
                    "Definition": {
                        "S": " To work at; to work; to till; to cultivate by toil."}}}},{"PutRequest": {
                "Item": {
                    "Word": {
                        "S": "Lac"
                    },
                    "Definition": {
                        "S": " A resinous substance produced mainly on the banyan tree, but to some extent on other trees, by the  pn>Coccus lacca"}}}},{"PutRequest": {
                "Item": {
                    "Word": {
                        "S": "Lace"
                    },
                    "Definition": {
                        "S": " That which binds or holds, especially by being interwoven; a string, cord, or band, usually one passing through eyelet or other holes, and used in drawing and holding together parts of a garment, of a s"}}}},{"PutRequest": {
                "Item": {
                    "Word": {
                        "S": "Lace"
                    },
                    "Definition": {
                        "S": " To fasten with a lace; to draw together with a lace passed through eyelet holes; to unite with a lace or laces, or, figuratively. with anything resembling laces."}}}},{"PutRequest": {
                "Item": {
                    "Word": {
                        "S": "Lace"
                    },
                    "Definition": {
                        "S": " To be fastened with a lace, or laces;  s>as, these boots  x>lace"}}}},{"PutRequest": {
                "Item": {
                    "Word": {
                        "S": "Laced"
                    },
                    "Definition": {
                        "S": " Fastened with a lace or laces; decorated with narrow strips or braid. See  r>Lace"}}}}]}